noid_minter/__init__.py
noid_minter/minter.py
noid_minter-0.1.7.dist-info/METADATA
noid_minter-0.1.7.dist-info/WHEEL
noid_minter-0.1.7.dist-info/licenses/LICENSE.md
noid_minter-0.1.7.dist-info/RECORD
