Metadata-Version: 2.4
Name: noid-minter
Version: 0.1.7
Summary: An ARK minter based on Noid.
Project-URL: Repository, https://github.com/uklibraries/noid-minter/
Author-email: MLE Slone <m.slone@gmail.com>
License-File: LICENSE.md
Requires-Python: ~=3.12
Requires-Dist: pyrand48<0.2,>=0.1.4
